sdcpy/__init__.py
sdcpy/core.py
sdcpy/io.py
sdcpy/plotting.py
sdcpy/scale_dependent_correlation.py
sdcpy-0.7.0.dist-info/METADATA
sdcpy-0.7.0.dist-info/WHEEL
sdcpy-0.7.0.dist-info/licenses/LICENSE
sdcpy-0.7.0.dist-info/RECORD
