Metadata-Version: 2.4
Name: sdcpy
Version: 0.7.0
Summary: Scale Dependent Correlation in Python
Project-URL: Homepage, https://github.com/AlFontal/sdcpy
Project-URL: Documentation, https://sdcpy.readthedocs.io
Project-URL: Repository, https://github.com/AlFontal/sdcpy
Author-email: Alejandro Fontal <alejandrofontal92@gmail.com>
License-Expression: MIT
License-File: LICENSE
Classifier: Development Status :: 4 - Beta
Classifier: License :: OSI Approved :: MIT License
Classifier: Programming Language :: Python :: 3
Classifier: Programming Language :: Python :: 3.9
Classifier: Programming Language :: Python :: 3.10
Classifier: Programming Language :: Python :: 3.11
Classifier: Programming Language :: Python :: 3.12
Requires-Python: <3.13,>=3.9
Requires-Dist: matplotlib>=3.7.1
Requires-Dist: numpy>=1.24.3
Requires-Dist: pandas>=2.0.2
Requires-Dist: plotnine>=0.12.1
Requires-Dist: scipy>=1.10.1
Requires-Dist: seaborn>=0.12.2
Requires-Dist: tqdm>=4.65.0
